gateware/cores/util/filter/karlsen_lpf.sv
/*
    Karlsen Fast Ladder III low-pass filter.

    Inspired by:
    https://www.musicdsp.org/en/latest/Filters/240-karlsen-fast-ladder.html
*/

`default_nettype none

module karlsen_lpf #(
    parameter W = 16
)(
    input rst,
    input clk,
    input sample_clk,
    input signed [W-1:0] g,           // tan(pi * cutoff_freq / fs) => (0 is 0, 1 is about 0.2fs)
    input signed [W-1:0] resonance,   // 0 to 4 (self oscillation)
    input signed [W-1:0] sample_in,
    output logic signed [W-1:0] sample_out
);

// Not pipelined for now...
logic [3:0] state;

logic signed [(W*2)-1:0] in_ex;
logic signed [(W*2)-1:0] g_ex;
logic signed [(W*2)-1:0] resonance_ex;
logic signed [(W*2)-1:0] rezz;
logic signed [(W*2)-1:0] rezz_cliph;
logic signed [(W*2)-1:0] rezz_clip;
logic signed [(W*2)-1:0] sat;
logic signed [(W*2)-1:0] a1;
logic signed [(W*2)-1:0] a2;
logic signed [(W*2)-1:0] a3;
logic signed [(W*2)-1:0] a4;

assign in_ex = (W*2)'(sample_in);
assign g_ex  = (W*2)'(g > 0 ? g : 0);
assign resonance_ex  = (W*2)'(resonance > 0 ? resonance : 0) <<< 1;

assign rezz_cliph = (rezz      > 32000) ? 32000 : rezz;
assign rezz_clip = (rezz_cliph < -32000) ? -32000 : rezz_cliph;

always_ff @(posedge sample_clk) begin
    if (rst) begin
        state <= 0;
        rezz <= 0;
        sat <= 0;
        a1 <= 0;
        a2 <= 0;
        a3 <= 0;
        a4 <= 0;
        sample_out <= 0;
    end else begin
        // Resonance
        rezz <= (in_ex - (((sample_out - in_ex) * resonance_ex) >>> W));
        // Saturation
        sat <= rezz + (((-rezz + rezz_clip)*31)>>>5);
        // Ladder filter
        a1 <= a1 + (((-a1 + sat) * g_ex) >>> W);
        a2 <= a2 + (((-a2 + a1) * g_ex) >>> W);
        a3 <= a3 + (((-a3 + a2) * g_ex) >>> W);
        a4 <= a4 + (((-a4 + a3) * g_ex) >>> W);
        sample_out <= a4[W-1:0];
    end
end

`ifdef COCOTB_SIM
initial begin
  $dumpfile ("karlsen_lpf.vcd");
  $dumpvars;
  #1;
end
`endif

endmodule

gateware/cores/util/filter/karlsen_lpf.vcd
$date
	Fri Apr 14 18:56:01 2023
$end
$version
	Icarus Verilog
$end
$timescale
	1ps
$end
$scope module karlsen_lpf $end
$var wire 1 ! clk $end
$var wire 16 " g [15:0] $end
$var wire 16 # resonance [15:0] $end
$var wire 1 $ rst $end
$var wire 1 % sample_clk $end
$var wire 16 & sample_in [15:0] $end
$var wire 32 ' rezz_cliph [31:0] $end
$var wire 32 ( rezz_clip [31:0] $end
$var wire 32 ) resonance_ex [31:0] $end
$var wire 32 * in_ex [31:0] $end
$var wire 32 + g_ex [31:0] $end
$var parameter 32 , W $end
$var reg 32 - a1 [31:0] $end
$var reg 32 . a2 [31:0] $end
$var reg 32 / a3 [31:0] $end
$var reg 32 0 a4 [31:0] $end
$var reg 32 1 rezz [31:0] $end
$var reg 16 2 sample_out [15:0] $end
$var reg 32 3 sat [31:0] $end
$var reg 4 4 state [3:0] $end
$upscope $end
$enddefinitions $end
$comment Show the parameter values. $end
$dumpall
b10000 ,
$end
#0
$dumpvars
bx 4
bx 3
bx 2
bx 1
bx 0
bx /
bx .
bx -
b0 +
b0 *
b0 )
bx (
bx '
b0 &
1%
1$
b0 #
b0 "
0!
$end
#5333120
0%
#10666240
0$
b0 (
b0 '
b0 2
b0 0
b0 /
b0 .
b0 -
b0 3
b0 1
b0 4
1%
#15999360
0%
#21332480
b1110101001100000 )
b111010100110000 +
b111010100110000 #
b111010100110000 "
b10111101010001 *
b10111101010001 &
1%
#26665600
0%
#31998720
b11111111111111111101011110011000 *
b1101011110011000 &
b101101010100011 (
b101101010100011 '
b101101010100011 1
1%
#37331840
0%
#42664960
b11111111111111111111011101111011 *
b1111011101111011 &
b11111111111111111011001010011010 (
b11111111111111111011001010011010 '
b10100101111101 -
b1011010101 3
b11111111111111111011001010011010 1
1%
#47998080
0%
#53331200
b11111111111111111101100100011101 *
b1101100100011101 &
b11111111111111111110111110101111 (
b11111111111111111110111110101111 '
b1001011111101 .
b11111111111111111111001100010000 -
b11111111111111111111110110010100 3
b11111111111111111110111110101111 1
1%
#58664320
0%
#63997440
b11111111111111111100111101010101 *
b1100111101010101 &
b11111111111111111011010110000011 (
b11111111111111111011010110000011 '
b100010110001 /
b10001011111 .
b11111111111111111111000110000100 -
b11111111111111111111111101111101 3
b11111111111111111011010110000011 1
1%
#69330560
0%
#74663680
b10100101001011 *
b10100101001011 &
b11111111111111111010001011000111 (
b11111111111111111010001011000111 '
b1111111010 0
b11010110110 /
b11111111111111111111101110111101 .
b11111111111111111101011000001100 -
b11111111111111111111110110101100 3
b11111111111111111010001011000111 1
1%
#79996800
0%
#85329920
b11111111111111111101110011110111 *
b1101110011110111 &
b100111100011010 (
b100111100011010 '
b1111111010 2
b10100111010 0
b110110000 /
b11111111111111111110101001111100 .
b11111111111111111011111010010011 -
b11111111111111111111110100010110 3
b100111100011010 1
1%
#90663040
0%
#95996160
b1100110101011 *
b1100110101011 &
b11111111111111111011100101000000 (
b11111111111111111011100101000000 '
b10100111010 2
b1110011011 0
b11111111111111111111011100010000 /
b11111111111111111101011001100010 .
b10111011 -
b1001111000 3
b11111111111111111011100101000000 1
1%
#101329280
0%
#106662400
b11111111111111111101110011011101 *
b1101110011011101 &
b10110001100010 (
b10110001100010 '
b1110011011 2
b11111111111111111111110111011101 0
b11111111111111111110100000011010 /
b11111111111111111110100111000100 .
b11111111111111111110000000000010 -
b11111111111111111111110111001010 3
b10110001100010 1
1%
#111995520
0%
#117328640
b10101011110011 *
b10101011110011 &
b11111111111111111011100101100101 (
b11111111111111111011100101100101 '
b1111110111011101 2
b11111111111111111111001111100110 0
b11111111111111111110100011011101 /
b11111111111111111110010101001100 .
b1011111000 -
b101100011 3
b11111111111111111011100101100101 1
1%
#122661760
0%
#127994880
b11111111111111111110011101101110 *
b1110011101101110 &
b101010000111011 (
b101010000111011 '
b1111001111100110 2
b11111111111111111110111011011000 0
b11111111111111111110011100111011 /
b11111111111111111111001011100001 .
b11111111111111111110000101001010 -
b11111111111111111111110111001011 3
b101010000111011 1
1%
#133328000
0%
#138661120
b101111111111 *
b101111111111 &
b11111111111111111101110000000100 (
b11111111111111111101110000000100 '
b1110111011011000 2
b11111111111111111110101101011011 0
b11111111111111111110110010010000 /
b11111111111111111110101011010011 .
b1010111100111 -
b1010100001 3
b11111111111111111101110000000100 1
1%
#143994240
0%
#149327360
b11111111111111111111101000100010 *
b1111101000100010 &
b10011010110000 (
b10011010110000 '
b1110101101011011 2
b11111111111111111110101111101000 0
b11111111111111111110101111000100 /
b11111111111111111111111010001011 .
b11111111111111111111101101100111 -
b11111111111111111111111011100000 3
b10011010110000 1
1%
#154660480
0%
#159993600
b110100001 *
b110100001 &
b11110101010 (
b11110101010 '
b1110101111101000 2
b11111111111111111110101111010111 0
b11111111111111111111010001011100 /
b11111111111111111111110100011010 .
b111100110111 -
b100110101 3
b11110101010 1
1%
#165326720
0%
#170659840
b1001100110101 *
b1001100110101 &
b1010110000101 (
b1010110000101 '
b1110101111010111 2
b11111111111111111110111110111101 0
b11111111111111111111100001011100 /
b10101100100 .
b101111000010 -
b111101 3
b1010110000101 1
1%
#175992960
0%
#181326080
b10011100010101 *
b10011100010101 &
b11011101000000 (
b11011101000000 '
b1110111110111101 2
b11111111111111111111001110101111 0
b11111111111111111111111001010011 /
b100001001110 .
b1000000111001 -
b10101100 3
b11011101000000 1
1%
#186659200
0%
#191992320
b11111111111111111100101100111011 *
b1100101100111011 &
b101100111000001 (
b101100111000001 '
b1111001110101111 2
b11111111111111111111100010001101 0
b1011100100 /
b101111101101 .
b10001000010110 -
b110111010 3
b101100111000001 1
1%
#197325440
0%
#202658560
b11000100011011 *
b11000100011011 &
b11111111111111111010011000110010 (
b11111111111111111010011000110010 '
b1111100010001101 2
b11111111111111111111110101001000 0
b11100000110 /
b1011000010001 .
b11101110010001 -
b1011001110 3
b11111111111111111010011000110010 1
1%
#207991680
0%
#213324800
b11111111111111111110000011110111 *
b1110000011110111 &
b110010011100011 (
b110010011100011 '
b1111110101001000 2
b110111101 0
b110111101000 /
b10011100111011 .
b11111111111111111111011100110000 -
b11111111111111111111110100110001 3
b110010011100011 1
1%
#218657920
0%
#223991040
b11001010011001 *
b11001010011001 &
b11111111111111111100011100001011 (
b11111111111111111100011100001011 '
b110111101 2
b11101001110 0
b1100101111111 /
b1000100111100 .
b10100101100111 -
b1100100111 3
b11111111111111111100011100001011 1
1%
#229324160
0%
#234657280
b11111111111111111110101100101000 *
b1110101100101000 &
b101111101010101 (
b101111101010101 '
b11101001110 2
b111110100001 0
b1010110110110 /
b1110001001100 .
b11111111111111111111110001100000 -
b11111111111111111111111000111000 3
b101111101010101 1
1%
#239990400
0%
#245323520
b10111100110111 *
b10111100110111 &
b11111111111111111101000101100011 (
b11111111111111111101000101100011 '
b111110100001 2
b1001001101001 0
b1100010111001 /
b110110101111 .
b10100110101100 -
b1011111010 3
b11111111111111111101000101100011 1
1%
#250656640
0%
#255989760
b1101100011 *
b1101100011 &
b100110000100010 (
b100110000100010 '
b1001001101001 2
b1010101001100 0
b1001110101011 /
b1101001111110 .
b101000010 -
b11111111111111111111111010001011 3
b100110000100010 1
1%
#261322880
0%
#266656000
b1101000001010 *
b1101000001010 &
b11111111111111111111010110100010 (
b11111111111111111111010110100010 '
b1010101001100 2
b1010010001101 0
b1011011001010 /
b111011110000 .
b10001110001000 -
b1001100001 3
b11111111111111111111010110100010 1
1%
#271989120
0%
#277322240
b1110010001000 *
b1110010001000 &
b1111001100010 (
b1111001100010 '
b1010010001101 2
b1010110010011 0
b1001100110001 /
b1100001011101 .
b111010000101 -
b11111111111111111111111110101101 3
b1111001100010 1
1%
#282655360
0%
#287988480
b11111111111111111100101111011101 *
b1100101111011101 &
b10001111010111 (
b10001111010111 '
b1010110010011 2
b1010001111011 0
b1010110001111 /
b1001111011011 .
b1010111000111 -
b11110011 3
b10001111010111 1
1%
#293321600
0%
#298654720
b11111111111111111101111000110010 *
b1101111000110010 &
b11111111111111111000100001100001 (
b11111111111111111000100001100001 '
b1010001111011 2
b1010011111001 0
b1010011000111 /
b1010010111100 .
b1110000110110 -
b100011110 3
b11111111111111111000100001100001 1
1%
#303987840
0%
#309320960
b11111111111111111111001010100100 *
b1111001010100100 &
b11111111111111111010110001111111 (
b11111111111111111010110001111111 '
b1010011111001 2
b1010011100010 0
b1010011000001 /
b1100000101000 .
b11111111111111111101100010001001 -
b11111111111111111111110001000011 3
b11111111111111111010110001111111 1
1%
#314654080
0%
#319987200
b11001001000101 *
b11001001000101 &
b11111111111111111101001100110110 (
b11111111111111111101001100110110 '
b1010011100010 2
b1010011010010 0
b1011001001111 /
b11111111111111111111101100001000 .
b11111111111111111100010001100000 -
b11111111111111111111110101100011 3
b11111111111111111101001100110110 1
1%
#325320320
0%
#330653440
b10010011011000 *
b10010011011000 &
b100110100101101 (
b100110100101101 '
b1010011010010 2
b1010110000000 0
b100111010010 /
b11111111111111111110001000000010 .
b11111111111111111100101100101010 -
b11111111111111111111111010011001 3
b100110100101101 1
1%
#335986560
0%
#341319680
b11111111111111111101001110000110 *
b1101001110000110 &
b11001110000100 (
b11001110000100 '
b1010110000000 2
b1000000100111 0
b11111111111111111111011110011000 /
b11111111111111111101011110001100 .
b11010101101 -
b1001101001 3
b11001110000100 1
1%
#346652800
0%
#351985920
b11111111111111111110001000011011 *
b1110001000011011 &
b11111111111111111001011100011111 (
b11111111111111111001011100011111 '
b1000000100111 2
b10011101001 0
b11111111111111111110100011101100 /
b11111111111111111110110100011110 .
b1101100110011 -
b110011100 3
b11111111111111111001011100011111 1
1%
#357319040
0%
#362652160
b1010010100001 *
b1010010100001 &
b11111111111111111011011111110011 (
b11111111111111111011011111110011 '
b10011101001 2
b11111111111111111111100000011001 0
b11111111111111111110101011010111 /
b1000110110 .
b11111111111111111101111010111101 -
b11111111111111111111110010111000 3
b11111111111111111011011111110011 1
1%
#367985280
0%
#373318400
b11111111111111111111101010101000 *
b1111101010101000 &
b10001100000110 (
b10001100000110 '
b1111100000011001 2
b11111111111111111111001000000111 0
b11111111111111111111010110001001 /
b11111111111111111111000111111001 .
b11111111111111111100110011111011 -
b11111111111111111111110110111111 3
b10001100000110 1
1%
#378651520
0%
#383984640
b1101000110 *
b1101000110 &
b11111111111111111111110100000000 (
b11111111111111111111110100000000 '
b1111001000000111 2
b11111111111111111111001110100010 0
b11111111111111111111001111100111 /
b11111111111111111110000100001001 .
b11111111111111111111010001011110 -
b100011000 3
b11111111111111111111110100000000 1
1%
#389317760
0%
#394650880
b101000010001 *
b101000010001 &
b1001100010001 (
b1001100010001 '
b1111001110100010 2
b11111111111111111111001111000001 0
b11111111111111111110101101000100 /
b11111111111111111110100111100010 .
b11111111111111111111100001010001 -
b11111111111111111111111111101000 3
b1001100010001 1
1%
#399984000
0%
#405317120
b11000010110 *
b11000010110 &
b1111010011011 (
b1111010011011 '
b1111001111000001 2
b11111111111111111110111111011110 0
b11111111111111111110101010100001 /
b11111111111111111111000001111101 .
b10010001111 -
b10011000 3
b1111010011011 1
1%
#410650240
0%
#415983360
b11111111111111111111100010100000 *
b1111100010100000 &
b1011011011111 (
b1011011011111 '
b1110111111011110 2
b11111111111111111110110101111000 0
b11111111111111111110110101001111 /
b11111111111111111111100110101100 .
b1000001111011 -
b11110100 3
b1011011011111 1
1%
#421316480
0%
#426649600
b11111010011 *
b11111010011 &
b10100101 (
b10100101 '
b1110110101111000 2
b11111111111111111110110101100101 0
b11111111111111111111001011110111 /
b10000011100 .
b1001101100111 -
b10110110 3
b10100101 1
1%
#431982720
0%
#437315840
b11111111111111111101101011000100 *
b1101101011000100 &
b1111111110101 (
b1111111110101 '
b1110110101100101 2
b11111111111111111110111111110001 0
b11111111111111111111101011010000 /
b101100011100 .
b101011010000 -
b101 3
b1111111110101 1
1%
#442648960
0%
#447982080
b101010010 *
b101010010 &
b11111111111111111100100110110110 (
b11111111111111111100100110110110 '
b1110111111110001 2
b11111111111111111111010011101010 0
b1001000101 /
b101011111001 .
b1010001111101 -
b11111111 3
b11111111111111111100100110110110 1
1%
#453315200
0%
#458648320
b11111111111111111101101100110001 *
b1101101100110001 &
b1000100111100 (
b1000100111100 '
b1111010011101010 2
b11111111111111111111101100000111 0
b11001000000 /
b111101010100 .
b11111111111111111111001001000010 -
b11111111111111111111111001001101 3
b1000100111100 1
1%
#463981440
0%
#469314560
b1011110011 *
b1011110011 &
b11111111111111111100001110100101 (
b11111111111111111100001110100101 '
b1111101100000111 2
b101010 0
b101001100111 /
b1000000101 .
b1110000 -
b10001001 3
b11111111111111111100001110100101 1
1%
#474647680
0%
#479980800
b111011100011 *
b111011100011 &
b101000110100 (
b101000110100 '
b101010 2
b10011011001 0
b11010010000 /
b101001011 .
b11111111111111111110010010011011 -
b11111111111111111111111000011101 3
b101000110100 1
1%
#485313920
0%
#490647040
b11111111111111111101111000010011 *
b1101111000010011 &
b1110001011110 (
b1110001011110 '
b10011011001 2
b10110100001 0
b10000100110 /
b11111111111111111111010000101001 .
b11111111111111111111010111010000 -
b1010001 3
b1110001011110 1
1%
#495980160
0%
#501313280
b101111000011 *
b101111000011 &
b11111111111111111011101010010100 (
b11111111111111111011101010010100 '
b10110100001 2
b10011110011 0
b11111111111111111111110011010100 /
b11111111111111111111010011101010 .
b11101110110 -
b11100010 3
b11111111111111111011101010010100 1
1%
#506646400
0%
#511979520
b101111010001 *
b101111010001 &
b1000101100001 (
b1000101100001 '
b10011110011 2
b100111011 0
b11111111111111111111100100110100 /
b11111111111111111111110101100111 .
b11111111111111111110010001000100 -
b11111111111111111111110111010100 3
b1000101100001 1
1%
#517312640
0%
#522645760
b11111111111111111110101001010000 *
b1110101001010000 &
b1001000011011 (
b1001000011011 '
b100111011 2
b11111111111111111111110110001110 0
b11111111111111111111101100100000 /
b11111111111111111111000111100101 .
b11111111111111111111100011101010 -
b10001011 3
b1001000011011 1
1%
#527978880
0%
#533312000
b11111111111111111111011000000010 *
b1111011000000010 &
b11111111111111111101010101010101 (
b11111111111111111101010101010101 '
b1111110110001110 2
b11111111111111111111110001110001 0
b11111111111111111111011011100110 /
b11111111111111111111010100011011 .
b10001110010 -
b10010000 3
b11111111111111111101010101010101 1
1%
#538645120
0%
#543978240
b1100011110100 *
b1100011110100 &
b11111111111111111110111100011010 (
b11111111111111111110111100011010 '
b1111110001110001 2
b11111111111111111111100111100111 0
b11111111111111111111011000010011 /
b11111111111111111111110000100000 .
b11111111111111111110111011100000 -
b11111111111111111111111010101010 3
b11111111111111111110111100011010 1
1%
#549311360
0%
#554644480
b110111010011 *
b110111010011 &
b11001100001111 (
b11001100001111 '
b1111100111100111 2
b11111111111111111111100000100110 0
b11111111111111111111100011011000 /
b11111111111111111111011000001111 .
b11111111111111111110111011111010 -
b11111111111111111111111101111000 3
b11001100001111 1
1%
#559977600
0%
#565310720
b11111111111111111100110001101000 *
b1100110001101000 &
b10000000010001 (
b10000000010001 '
b1111100000100110 2
b11111111111111111111100001110111 0
b11111111111111111111011110010001 /
b11111111111111111111001011010001 .
b111000100100 -
b110011000 3
b10000000010001 1
1%
#570643840
0%
#575976960
b10001010101101 *
b10001010101101 &
b11111111111111111010010001011100 (
b11111111111111111010010001011100 '
b1111100001110111 2
b11111111111111111111100000001101 0
b11111111111111111111010101100100 /
b11111111111111111111111101010011 .
b1011001011000 -
b100000000 3
b11111111111111111010010001011100 1
1%
#581310080
0%
#586643200
b11111111111111111111100011110101 *
b1111100011110101 &
b100100101010011 (
b100100101010011 '
b1111100000001101 2
b11111111111111111111011011010101 0
b11111111111111111111100111110000 /
b100111011100 .
b11111111111111111110001000101010 -
b11111111111111111111110100100010 3
b100100101010011 1
1%
#591976320
0%
#597309440
b11111111111111111110001111001001 *
b1110001111001001 &
b11111111111111111111100111001010 (
b11111111111111111111100111001010 '
b1111011011010101 2
b11111111111111111111100001000000 0
b100111001 /
b11111111111111111111011110110000 .
b1000101100011 -
b1001001010 3
b11111111111111111111100111001010 1
1%
#602642560
0%
#607975680
b11111111111111111100101110111000 *
b1100101110111000 &
b11111111111111111101001001011001 (
b11111111111111111101001001011001 '
b1111100001000000 2
b11111111111111111111110001011011 0
b11111111111111111111110011011011 /
b1101110011 .
b11010010101 -
b11111111111111111111111111001110 3
b11111111111111111101001001011001 1
1%
#613308800
0%
#618641920
b1001101010 *
b1001101010 &
b11111111111111111010001011110011 (
b11111111111111111010001011110011 '
b1111110001011011 2
b11111111111111111111110010010101 0
b11111111111111111111111111011111 /
b10011100010 .
b11111111111111111110111010101011 -
b11111111111111111111111010010010 3
b11111111111111111010001011110011 1
1%
#623975040
0%
#629308160
b11111111111111111110101010011110 *
b1110101010011110 &
b11111110110 (
b11111110110 '
b1111110010010101 2
b11111111111111111111111000010110 0
b1000101010 /
b11111111111111111111101010110110 .
b11111111111111111100110000000001 -
b11111111111111111111110100010111 3
b11111110110 1
1%
#634641280
0%
#639974400
b11111111111111111110101000010111 *
b1110101000010111 &
b11111111111111111101101000101100 (
b11111111111111111101101000101100 '
b1111111000010110 2
b11111111111111111111111111110011 0
b11111111111111111111111011000000 /
b11111111111111111110010101010100 .
b11111111111111111110011101110011 -
b111111 3
b11111111111111111101101000101100 1
1%
#645307520
0%
#650640640
b10011101100001 *
b10011101100001 &
b11111111111111111101011111001001 (
b11111111111111111101011111001001 '
b1111111111110011 2
b11111111111111111111111101100110 0
b11111111111111111111001100011100 /
b11111111111111111110011001001100 .
b11111111111111111110000101011111 -
b11111111111111111111111011010001 3
b11111111111111111101011111001001 1
1%
#655973760
0%
#661306880
b110101111001 *
b110101111001 &
b100101101111011 (
b100101101111011 '
b1111111101100110 2
b11111111111111111111100111000101 0
b11111111111111111110110100111110 /
b11111111111111111110010000001010 .
b11111111111111111101110011111011 -
b11111111111111111111111010111110 3
b100101101111011 1
1%
#666640000
0%
#671973120
b1011101110011 *
b1011101110011 &
b1101001011100 (
b1101001011100 '
b1111100111000101 2
b11111111111111111111010000001000 0
b11111111111111111110100100000111 /
b11111111111111111110000011001110 .
b111110010000 -
b1001011011 3
b1101001011100 1
1%
#677306240
0%
#682639360
b1101001100 *
b1101001100 &
b11001010100000 (
b11001010100000 '
b1111010000001000 2
b11111111111111111110111011111110 0
b11111111111111111110010101000011 /
b11111111111111111111011000110101 .
b1010010000001 -
b11010010 3
b11001010100000 1
1%
#687972480
0%
#693305600
b11011001000111 *
b11011001000111 &
b1000101000110 (
b1000101000110 '
b1110111011111110 2
b11111111111111111110101010001001 0
b11111111111111111110110100000100 /
b10000010011 .
b10001001001010 -
b110010101 3
b1000101000110 1
1%
#698638720
0%
#703971840
b11111111111111111110011011011010 *
b1110011011011010 &
b111011110001011 (
b111011110001011 '
b1110101010001001 2
b11111111111111111110101110101011 0
b11111111111111111111011110010010 /
b1000111100111 .
b1101001111111 -
b10001010 3
b111011110001011 1
1%
#709304960
0%
#714638080
b100110100010 *
b100110100010 &
b11111111111111111110001101111011 (
b11111111111111111110001101111011 '
b1110101110101011 2
b11111111111111111111000100011101 0
b1110011111 /
b1010111010110 .
b100010100010110 -
b1110111100 3
b11111111111111111110001101111011 1
1%
#719971200
0%
#725304320
b11111111111111111111010110001001 *
b1111010110001001 &
b10010100010010 (
b10010100010010 '
b1111000100011101 2
b11111111111111111111100110010101 0
b101111110101 /
b10101101110111 .
b1100001100111 -
b11111111111111111111111100011011 3
b10010100010010 1
1%
#730637440
0%
#735970560
b11111111111111111101000000100010 *
b1101000000100010 &
b11111111111111111111100110010110 (
b11111111111111111111100110010110 '
b1111100110010101 2
b111111110 0
b1101001100001 /
b10001010111101 .
b1111000110011 -
b100101000 3
b11111111111111111111100110010110 1
1%
#741303680
0%
#746636800
b11111111111111111111101101111110 *
b1111101101111110 &
b11111111111111111010101000110000 (
b11111111111111111010101000110000 '
b111111110 2
b110100100111 0
b1111000110100 /
b10000010101001 .
b110101110000 -
b11111111111111111111111111001100 3
b11111111111111111010101000110000 1
1%
#751969920
0%
#757303040
b11111111111111111100111000010000 *
b1100111000010000 &
b11111111111111111111010110001011 (
b11111111111111111111010110001011 '
b110100100111 2
b1010011110101 0
b1111101010011 /
b1011111011100 .
b11111111111111111110000000000001 -
b11111111111111111111110101010001 3
b11111111111111111111010110001011 1
1%
#762636160
0%
#767969280
b10100111000000 *
b10100111000000 &
b11111111111111111001010001001110 (
b11111111111111111001010001001110 '
b1010011110101 2
b1100110110011 0
b1101111101000 /
b11111111111111111111111001001010 .
b11111111111111111110100111011101 -
b11111111111111111111111110101100 3
b11111111111111111001010001001110 1
1%
#773302400
0%
#778635520
b11111111111111111101000111000011 *
b1101000111000011 &
b11110011001010 (
b11110011001010 '
b1100110110011 2
b1101010110101 0
b111001011001 /
b11111111111111111111010011110000 .
b11111111111111111100001010110010 -
b11111111111111111111110010100010 3
b11110011001010 1
1%
#783968640
0%
#789301760
b11111111111111111101001000010111 *
b1101001000010111 &
b11111111111111111000111111100111 (
b11111111111111111000111111100111 '
b1101010110101 2
b1010100001100 0
b1010110111 /
b11111111111111111101110111110000 .
b11111111111111111111101010010101 -
b111100110 3
b11111111111111111000111111100111 1
1%
#794634880
0%
#799968000
b11111111111111111111100110011000 *
b1111100110011000 &
b11111111111111111000111110011100 (
b11111111111111111000111110011100 '
b1010100001100 2
b110010100111 0
b11111111111111111111000111100001 /
b11111111111111111110101100001100 .
b11111111111111111100100110111111 -
b11111111111111111111110001111111 3
b11111111111111111000111110011100 1
1%
#805301120
0%
#810634240
b10100111001000 *
b10100111001000 &
b11111111111111111110000001110110 (
b11111111111111111110000001110110 '
b110010100111 2
b1100101 0
b11111111111111111110111011000000 /
b11111111111111111101101111001101 .
b11111111111111111010111100100010 -
b11111111111111111111110001111100 3
b11111111111111111110000001110110 1
1%
#815967360
0%
#821300480
b11111111111111111110111100110111 *
b1110111100110111 &
b100010001110100 (
b100010001110100 '
b1100101 2
b11111111111111111111100001010001 0
b11111111111111111110011000010011 /
b11111111111111111100011101011010 .
b11111111111111111100010110110110 -
b11111111111111111111111100000011 3
b100010001110100 1
1%
#826633600
0%
#831966720
b11111111111111111101111110000000 *
b1101111110000000 &
b11111111111111111101111101111101 (
b11111111111111111101111101111101 '
b1111100001010001 2
b11111111111111111110111111110111 0
b11111111111111111101100000000010 /
b11111111111111111100011010011001 .
b11111111111111111111111110111010 -
b1000100011 3
b11111111111111111101111101111101 1
1%
#837299840
0%
#842632960
b1000100000001 *
b1000100000001 &
b11111111111111111100100011001000 (
b11111111111111111100100011001000 '
b1110111111110111 2
b11111111111111111110010011111111 0
b11111111111111111101000000001001 /
b11111111111111111110000010111111 .
b11111111111111111111000011111000 -
b11111111111111111111111011111011 3
b11111111111111111100100011001000 1
1%
#847966080
0%
#853299200
b11101001101010 *
b11101001101010 &
b10111101000001 (
b10111101000001 '
b1110010011111111 2
b11111111111111111101101101100110 0
b11111111111111111101011110101111 /
b11111111111111111110100000101100 .
b11111111111111111101111010010010 -
b11111111111111111111111001000110 3
b10111101000001 1
1%
#858632320
0%
#863965440
b11011111001011 *
b11011111001011 &
b111110100000000 (
b111110100000000 '
b1101101101100110 2
b11111111111111111101100110110010 0
b11111111111111111101111100111011 /
b11111111111111111110001111000110 .
b1110000001 -
b101111010 3
b1000100010011110 1
1%
#869298560
0%
#874631680
b11111111111111111111010010001000 *
b1111010010001000 &
b1101100110110010 2
b11111111111111111101110000111010 0
b11111111111111111110000101001111 /
b11111111111111111111001001001100 .
b100000001110000 -
b11111111111111111111100100000011 3
b1000110001100010 1
1%
#879964800
0%
#885297920
b10000010101110 *
b10000010101110 &
b110100011010 (
b110100011010 '
b1101110000111010 2
b11111111111111111101111010001101 0
b11111111111111111110100100010101 /
b1011000010001 .
b110001100110011 -
b11111111111111111111010101111100 3
b110100011010 1
1%
#890631040
0%
#895964160
b1110000000000 *
b1110000000000 &
b101111101011010 (
b101111101011010 '
b1101111010001101 2
b11111111111111111110001101011111 0
b11111111111111111111110110101100 /
b11100101100000 .
b11101111001001 -
b1101000 3
b101111101011010 1
1%
#901297280
0%
#906630400
b11100011001011 *
b11100011001011 &
b101010001000011 (
b101010001000011 '
b1110001101011111 2
b11111111111111111110111101101001 0
b1100100000000 /
b11101001111010 .
b100110000010000 -
b1011111010 3
b101010001000011 1
1%
#911963520
0%
#917296640
b11111111111111111110010110011000 *
b1110010110011000 &
b111110100000000 (
b111110100000000 '
b1110111101101001 2
b1001110010 0
b10100001010011 /
b100001010000110 .
b100111111010000 -
b1010100010 3
b1000011100000000 1
1%
#922629760
0%
#927962880
b11111111111111111111100011010100 *
b1111100011010100 &
b11111111111111111101110010011100 (
b11111111111111111101110010011100 '
b1001110010 2
b1001111001000 0
b11010001010001 /
b100100010011011 .
b110100100010011 -
b11111111111111111111101010001000 3
b11111111111111111101110010011100 1
1%
#933296000
0%
#938629120
b111000110110 *
b111000110110 &
b11111111111111111111000000000110 (
b11111111111111111111000000000110 '
b1001111001000 2
b10001010101100 0
b11110110011010 /
b101011101110111 .
b10100011000110 -
b11111111111111111111111011100100 3
b11111111111111111111000000000110 1
1%
#943962240
0%
#949295360
b10000010110101 *
b10000010110101 &
b100100011101 (
b100100011101 '
b10001010101100 2
b10111011111111 0
b100100101110000 /
b100001000010111 .
b111011001011 -
b11111111111111111111111110000000 3
b100100011101 1
1%
#954628480
0%
#959961600
b11100011111011 *
b11100011111011 &
b1111011101001 (
b1111011101001 '
b10111011111111 2
b11101100011001 0
b100011000010010 /
b10101010011011 .
b110000110001 -
b1001000 3
b1111011101001 1
1%
#965294720
0%
#970627840
b11111111111111111110011001100100 *
b1110011001100100 &
b100001000100000 (
b100001000100000 '
b11101100011001 2
b100000000011110 0
b11100101111111 /
b1110010101110 .
b1010011000010 -
b11110111 3
b100001000100000 1
1%
#975960960
0%
#981294080
b10101100111001 *
b10101100111001 &
b11111111111111111001100011010111 (
b11111111111111111001100011010111 '
b100000000011110 2
b11110100010110 0
b10110001001110 /
b1100100001101 .
b10100110000110 -
b1000010001 3
b11111111111111111001100011010111 1
1%
#986627200
0%
#991960320
b1000011001111 *
b1000011001111 &
b1100000011000 (
b1100000011000 '
b11110100010110 2
b11010101100111 0
b10001101111101 /
b10000010010111 .
b11111111111111111110011101001010 -
b11111111111111111111110011000110 3
b1100000011000 1
1%
#997293440
0%
#1002626560
b110110001011 *
b110110001011 &
b11111111111111111110100001000110 (
b11111111111111111110100001000110 '
b11010101100111 2
b10110100110011 0
b10001000101001 /
b11001011100 .
b11111111111111111111110110100001 -
b11000000 3
b11111111111111111110100001000110 1
1%
#1007959680
0%
#1013292800
b1011100010110 *
b1011100010110 &
b11111111111111111110100100001101 (
b11111111111111111110100100001101 '
b10110100110011 2
b10100000100101 0
b1010101101111 /
b1001011100 .
b11111111111111111111001111011010 -
b11111111111111111111111101000010 3
b11111111111111111110100100001101 1
1%
#1018625920
0%
#1023959040
b110100101101 *
b110100101101 &
b1011011000 (
b1011011000 '
b10100000100101 2
b1111110010100 0
b110010110011 /
b11111111111111111111101110110111 .
b11111111111111111110111011101000 -
b11111111111111111111111101001000 3
b1011011000 1
1%
#1029292160
0%
#1034625280
b11111111111111111111000110111010 *
b1111000110111010 &
b11111111111111111111010001111101 (
b11111111111111111111010001111101 '
b1111110010100 2
b1011011101111 0
b10011101100 /
b11111111111111111111010111011001 .
b11111111111111111111100000001000 -
b10110 3
b11111111111111111111010001111101 1
1%
#1039958400
0%
